{
  "dataset_revision": "e7a26af6f3ae46b30dde8737f02c07b1505bcc73",
  "evaluation_time": 157.8729226589203,
  "kg_co2_emissions": null,
  "mteb_version": "1.14.19",
  "scores": {
    "test": [
      {
        "hf_subset": "default",
        "languages": [
          "eng-Latn"
        ],
        "main_score": 0.32845678640225423,
        "v_measure": 0.32845678640225423,
        "v_measure_std": 0.013319322599227235,
        "v_measures": [
          0.29863473534345264,
          0.3198524007912311,
          0.32324776632983576,
          0.3327975330956136,
          0.3203404540300012,
          0.34240526569393515,
          0.34511181574621713,
          0.32681111532027735,
          0.34287394976565133,
          0.3324928279063273
        ]
      }
    ]
  },
  "task_name": "MedrxivClusteringP2P"
}