{
  "dataset_revision": "79531abbd1fb92d06c6d6315a0cbbbf5bb247ea4",
  "mteb_dataset_name": "CQADupstackPhysicsRetrieval",
  "mteb_version": "1.10.3",
  "test": {
    "evaluation_time": 408.06,
    "map_at_1": 0.31052,
    "map_at_10": 0.41566,
    "map_at_100": 0.42924,
    "map_at_1000": 0.43023,
    "map_at_20": 0.42333,
    "map_at_3": 0.38459,
    "map_at_5": 0.40354,
    "mrr_at_1": 0.37729,
    "mrr_at_10": 0.47367,
    "mrr_at_100": 0.48136,
    "mrr_at_1000": 0.48179,
    "mrr_at_20": 0.47806,
    "mrr_at_3": 0.44883,
    "mrr_at_5": 0.46442,
    "ndcg_at_1": 0.37729,
    "ndcg_at_10": 0.47411,
    "ndcg_at_100": 0.52887,
    "ndcg_at_1000": 0.54678,
    "ndcg_at_20": 0.49647,
    "ndcg_at_3": 0.42592,
    "ndcg_at_5": 0.45133,
    "precision_at_1": 0.37729,
    "precision_at_10": 0.08422,
    "precision_at_100": 0.013,
    "precision_at_1000": 0.00161,
    "precision_at_20": 0.04957,
    "precision_at_3": 0.20051,
    "precision_at_5": 0.14264,
    "recall_at_1": 0.31052,
    "recall_at_10": 0.58963,
    "recall_at_100": 0.81719,
    "recall_at_1000": 0.93368,
    "recall_at_20": 0.6673,
    "recall_at_3": 0.45515,
    "recall_at_5": 0.52054
  }
}