{
  "dataset_revision": "1399c76144fd37290681b995c656ef9b2e06e26d",
  "evaluation_time": 98.41781759262085,
  "kg_co2_emissions": null,
  "mteb_version": "1.13.1",
  "scores": {
    "test": [
      {
        "accuracy": 0.48319999999999996,
        "f1": 0.478496439518891,
        "f1_weighted": 0.47849643951889104,
        "hf_subset": "en",
        "languages": [
          "eng-Latn"
        ],
        "main_score": 0.48319999999999996,
        "scores_per_experiment": [
          {
            "accuracy": 0.485,
            "f1": 0.48552454605416334,
            "f1_weighted": 0.48552454605416334
          },
          {
            "accuracy": 0.4818,
            "f1": 0.4791692082814979,
            "f1_weighted": 0.47916920828149795
          },
          {
            "accuracy": 0.4682,
            "f1": 0.46859167879394387,
            "f1_weighted": 0.468591678793944
          },
          {
            "accuracy": 0.4714,
            "f1": 0.47144822517757506,
            "f1_weighted": 0.4714482251775751
          },
          {
            "accuracy": 0.4906,
            "f1": 0.47335344720171335,
            "f1_weighted": 0.47335344720171335
          },
          {
            "accuracy": 0.478,
            "f1": 0.47138083544766385,
            "f1_weighted": 0.4713808354476638
          },
          {
            "accuracy": 0.4856,
            "f1": 0.4808305330870185,
            "f1_weighted": 0.48083053308701856
          },
          {
            "accuracy": 0.5156,
            "f1": 0.5169210117870907,
            "f1_weighted": 0.5169210117870907
          },
          {
            "accuracy": 0.4948,
            "f1": 0.49092517038608746,
            "f1_weighted": 0.49092517038608746
          },
          {
            "accuracy": 0.461,
            "f1": 0.44681973897215627,
            "f1_weighted": 0.4468197389721563
          }
        ]
      }
    ]
  },
  "task_name": "AmazonReviewsClassification"
}